{
  "m_header": {
    "m_packetFormat": 2022,
    "m_gameMajorVersion": 1,
    "m_gameMinorVersion": 3,
    "m_packetVersion": 1,
    "m_packetId": 11,
    "m_sessionUID": "12415723118142429171",
    "m_sessionTime": 0,
    "m_frameIdentifier": 0,
    "m_playerCarIndex": 19,
    "m_secondaryPlayerCarIndex": 255
  },
  "m_carIdx": 18,
  "m_numLaps": 6,
  "m_numTyreStints": 1,
  "m_bestLapTimeLapNum": 2,
  "m_bestSector1LapNum": 2,
  "m_bestSector2LapNum": 1,
  "m_bestSector3LapNum": 1,
  "m_lapHistoryData": [
    [null],
    [null],
    [null],
    [null],
    [null],
    [null],
    [null],
    [null],
    [null],
    [null],
    [null],
    [null],
    [null],
    [null],
    [null],
    [null],
    [null],
    [null],
    [null],
    [null],
    [null],
    [null],
    [null],
    [null],
    [null],
    [null],
    [null],
    [null],
    [null],
    [null],
    [null],
    [null],
    [null],
    [null],
    [null],
    [null],
    [null],
    [null],
    [null],
    [null],
    [null],
    [null],
    [null],
    [null],
    [null],
    [null],
    [null],
    [null],
    [null],
    [null],
    [null],
    [null],
    [null],
    [null],
    [null],
    [null],
    [null],
    [null],
    [null],
    [null],
    [null],
    [null],
    [null],
    [null],
    [null],
    [null],
    [null],
    [null],
    [null],
    [null],
    [null],
    [null],
    [null],
    [null],
    [null],
    [null],
    [null],
    [null],
    [null],
    [null],
    [null],
    [null],
    [null],
    [null],
    [null],
    [null],
    [null],
    [null],
    [null],
    [null],
    [null],
    [null],
    [null],
    [null],
    [null],
    [null],
    [null],
    [null],
    [null],
    [null]
  ],
  "m_tyreStintsHistoryData": [
    [null],
    [null],
    [null],
    [null],
    [null],
    [null],
    [null],
    [null]
  ]
}
